invokeai_mcp_server.py
invokeai_mcp_server-1.0.1.dist-info/licenses/LICENSE
invokeai_mcp_server-1.0.1.dist-info/METADATA
invokeai_mcp_server-1.0.1.dist-info/WHEEL
invokeai_mcp_server-1.0.1.dist-info/entry_points.txt
invokeai_mcp_server-1.0.1.dist-info/top_level.txt
invokeai_mcp_server-1.0.1.dist-info/RECORD
