Metadata-Version: 2.4
Name: invokeai-mcp-server
Version: 1.0.1
Summary: A Model Context Protocol server for InvokeAI image generation
Author-email: CoinsTax LLC <support@coinstax.com>
Maintainer-email: CoinsTax LLC <support@coinstax.com>
License: MIT
Project-URL: Homepage, https://github.com/coinstax/invokeai-mcp-server
Project-URL: Documentation, https://github.com/coinstax/invokeai-mcp-server#readme
Project-URL: Repository, https://github.com/coinstax/invokeai-mcp-server
Project-URL: Issues, https://github.com/coinstax/invokeai-mcp-server/issues
Project-URL: Changelog, https://github.com/coinstax/invokeai-mcp-server/blob/main/CHANGELOG.md
Keywords: mcp,model-context-protocol,invokeai,stable-diffusion,sdxl,image-generation,ai,claude,lora,text-to-image,img2img
Classifier: Development Status :: 5 - Production/Stable
Classifier: Intended Audience :: Developers
Classifier: Topic :: Software Development :: Libraries :: Python Modules
Classifier: Topic :: Multimedia :: Graphics
Classifier: Topic :: Scientific/Engineering :: Artificial Intelligence
Classifier: License :: OSI Approved :: MIT License
Classifier: Programming Language :: Python :: 3
Classifier: Programming Language :: Python :: 3.8
Classifier: Programming Language :: Python :: 3.9
Classifier: Programming Language :: Python :: 3.10
Classifier: Programming Language :: Python :: 3.11
Classifier: Programming Language :: Python :: 3.12
Classifier: Operating System :: OS Independent
Classifier: Environment :: Console
Requires-Python: >=3.8
License-File: LICENSE
Requires-Dist: httpx>=0.24.0
Requires-Dist: mcp>=0.1.0
Dynamic: license-file
